flywheel_alt_data_sdk/__init__.py
flywheel_alt_data_sdk/flywheel_alt_data_sdk.py
flywheel_alt_data_sdk/service/__init__.py
flywheel_alt_data_sdk/service/ecom_insights_model.py
flywheel_alt_data_sdk/service/ticker_mapping.py
flywheel_alt_data_sdk-1.0.4.dist-info/METADATA
flywheel_alt_data_sdk-1.0.4.dist-info/WHEEL
flywheel_alt_data_sdk-1.0.4.dist-info/top_level.txt
flywheel_alt_data_sdk-1.0.4.dist-info/RECORD
