Metadata-Version: 2.1
Name: flywheel-alt-data-sdk
Version: 1.0.4
Summary: A Python wrapper for the Flywheel Digital Alt Data API
Requires-Python: >=3.7
Requires-Dist: requests
